cdk_triggers/__init__.py
cdk_triggers/py.typed
cdk_triggers/_jsii/__init__.py
cdk_triggers/_jsii/cdk-triggers@0.1.35.jsii.tgz
cdk_triggers-0.1.35.dist-info/LICENSE
cdk_triggers-0.1.35.dist-info/METADATA
cdk_triggers-0.1.35.dist-info/NOTICE
cdk_triggers-0.1.35.dist-info/WHEEL
cdk_triggers-0.1.35.dist-info/top_level.txt
cdk_triggers-0.1.35.dist-info/RECORD
