Metadata-Version: 2.1
Name: cdk-triggers
Version: 0.1.35
Summary: Execute AWS Lambda handlers during deployments of AWS CDK stacks
Home-page: https://github.com/awslabs/cdk-triggers.git
Author: Amazon Web Services<aws-cdk-team@amazon.com>
License: Apache-2.0
Project-URL: Source, https://github.com/awslabs/cdk-triggers.git
Platform: UNKNOWN
Classifier: Intended Audience :: Developers
Classifier: Operating System :: OS Independent
Classifier: Programming Language :: JavaScript
Classifier: Programming Language :: Python :: 3 :: Only
Classifier: Programming Language :: Python :: 3.6
Classifier: Programming Language :: Python :: 3.7
Classifier: Programming Language :: Python :: 3.8
Classifier: Programming Language :: Python :: 3.9
Classifier: Typing :: Typed
Classifier: Development Status :: 7 - Inactive
Classifier: License :: OSI Approved
Requires-Python: >=3.6
License-File: LICENSE
License-File: NOTICE
Requires-Dist: aws-cdk-lib (<3.0.0,>=2.0.0)
Requires-Dist: constructs (<11.0.0,>=10.0.5)
Requires-Dist: jsii (<2.0.0,>=1.54.0)
Requires-Dist: publication (>=0.0.3)
